{"stat.walkOneCm":65193,"achievement.openInventory":6,"stat.useItem.minecraft.barrier":34,"stat.leaveGame":7,"stat.damageTaken":1860,"stat.entityKilledBy.Creeper":1,"stat.flyOneCm":108210,"stat.deaths":8,"stat.useItem.minecraft.bedrock":2,"stat.jump":214,"stat.swimOneCm":41,"stat.playOneMinute":39160,"stat.fallOneCm":7914,"stat.entityKilledBy.Zombie":2,"stat.useItem.minecraft.sea_lantern":7,"stat.entityKilledBy.Skeleton":2,"stat.crouchOneCm":412,"stat.timeSinceDeath":79,"stat.useItem.minecraft.dirt":6,"stat.sprintOneCm":19025,"stat.useItem.minecraft.sign":7,"stat.mineBlock.minecraft.tallgrass":2,"achievement.exploreAllBiomes":{"value":0,"progress":["Beach","Ocean","River","Plains"]},"stat.diveOneCm":1180}